megatron_fsdp/__init__.py
megatron_fsdp/distributed_data_parallel_config.py
megatron_fsdp/fully_shard.py
megatron_fsdp/megatron_fsdp.py
megatron_fsdp/package_info.py
megatron_fsdp/param_and_grad_buffer.py
megatron_fsdp/uneven_dtensor.py
megatron_fsdp/utils.py
megatron_fsdp-0.2.2.dist-info/METADATA
megatron_fsdp-0.2.2.dist-info/WHEEL
megatron_fsdp-0.2.2.dist-info/top_level.txt
megatron_fsdp-0.2.2.dist-info/RECORD
