Metadata-Version: 2.4
Name: megatron-fsdp
Version: 0.2.2
Summary: **Megatron-FSDP** is an NVIDIA-developed PyTorch extension that provides a high-performance implementation of Fully Sharded Data Parallelism (FSDP)
Author-email: NVIDIA <nemo-toolkit@nvidia.com>
Maintainer-email: NVIDIA <nemo-toolkit@nvidia.com>
License: Apache 2.0
Project-URL: Download, https://github.com/NVIDIA/Megatron-LM/releases
Project-URL: Homepage, https://github.com/NVIDIA/Megatron-LM/megatron/core
Keywords: NLP,NLU,deep,gpu,language,learning,learning,machine,nvidia,pytorch,torch,transformer
Classifier: Development Status :: 5 - Production/Stable
Classifier: Environment :: Console
Classifier: Intended Audience :: Developers
Classifier: Intended Audience :: Information Technology
Classifier: Intended Audience :: Science/Research
Classifier: License :: OSI Approved :: BSD License
Classifier: Natural Language :: English
Classifier: Operating System :: OS Independent
Classifier: Programming Language :: Python :: 3
Classifier: Programming Language :: Python :: 3.8
Classifier: Programming Language :: Python :: 3.9
Classifier: Topic :: Scientific/Engineering :: Artificial Intelligence
Classifier: Topic :: Scientific/Engineering :: Image Recognition
Classifier: Topic :: Scientific/Engineering :: Mathematics
Classifier: Topic :: Scientific/Engineering
Classifier: Topic :: Software Development :: Libraries :: Python Modules
Classifier: Topic :: Software Development :: Libraries
Classifier: Topic :: Utilities
Requires-Python: >=3.10
Requires-Dist: torch
Requires-Dist: einops
Requires-Dist: packaging
